x256numpy/__init__.py
x256numpy/x256.npz
x256numpy/x256.py
x256numpy-0.0.1.dist-info/LICENSE
x256numpy-0.0.1.dist-info/METADATA
x256numpy-0.0.1.dist-info/WHEEL
x256numpy-0.0.1.dist-info/top_level.txt
x256numpy-0.0.1.dist-info/RECORD
