Metadata-Version: 2.2
Name: x256numpy
Version: 0.0.1
Summary: Quickly find the nearest xterm 256 color index of an RGB (NumPy Version)
Author-email: userElaina <userelaina@pm.me>
Maintainer-email: userElaina <userelaina@pm.me>
License: MIT License
Project-URL: Homepage, https://github.com/userElaina/python-x256-numpy
Project-URL: Bug Reports, https://github.com/userElaina/python-x256-numpy/issues
Project-URL: Source, https://github.com/userElaina/python-x256-numpy
Keywords: x256,xterm,color
Classifier: License :: OSI Approved :: MIT License
Classifier: Programming Language :: Python :: 3
Requires-Python: >=3.9
License-File: LICENSE
Requires-Dist: numpy
Provides-Extra: dev
Requires-Dist: x256offline>=0.0.4; extra == "dev"
